ACSNI/__init__.py
ACSNI/corep.py
ACSNI/dat.py
ACSNI/dbs.py
ACSNI/mud.py
ACSNI/network.py
ACSNI/sim.py
ACSNI/utility.py
ACSNI-1.0.6.data/scripts/ACSNI-derive
ACSNI-1.0.6.data/scripts/ACSNI-get
ACSNI-1.0.6.data/scripts/ACSNI-run
ACSNI-1.0.6.data/scripts/ACSNI-split
ACSNI-1.0.6.dist-info/METADATA
ACSNI-1.0.6.dist-info/WHEEL
ACSNI-1.0.6.dist-info/top_level.txt
ACSNI-1.0.6.dist-info/RECORD
