Metadata-Version: 2.1
Name: ACSNI
Version: 1.0.6
Summary: automatic context-specific network inference
Home-page: https://github.com/caanene1/ACSNI
Author: Chinedu A. Anene
Author-email: caanenedr@outlook.com
License: UNKNOWN
Download-URL: https://github.com/caanene1/ACSNI/releases/download/1.0.6/ACSNI-1.0.6-py3-none-any.whl
Platform: UNKNOWN
Classifier: Programming Language :: Python :: 3
Classifier: License :: OSI Approved :: MIT License
Classifier: Operating System :: OS Independent
Requires-Python: >=3.8
Requires-Dist: numpy (~=1.19.5)
Requires-Dist: pandas (~=1.2.3)
Requires-Dist: scikit-learn (>=0.24.1)
Requires-Dist: scipy (>=1.5.4)
Requires-Dist: tensorflow (~=2.4.1)
